sharpapi/__init__.py
sharpapi/dto/__init__.py
sharpapi/dto/job_description_parameters.py
sharpapi/dto/sharp_api_job.py
sharpapi/dto/sharp_api_subscription_info.py
sharpapi/enums/__init__.py
sharpapi/enums/sharp_api_job_status_enum.py
sharpapi/enums/sharp_api_job_type_enum.py
sharpapi/enums/sharp_api_languages.py
sharpapi/enums/sharp_api_voice_tone.py
sharpapi/sharp_api_service.py
sharpapi_python_client-1.0.2.dist-info/LICENSE
sharpapi_python_client-1.0.2.dist-info/METADATA
sharpapi_python_client-1.0.2.dist-info/WHEEL
sharpapi_python_client-1.0.2.dist-info/RECORD
