Metadata-Version: 2.1
Name: sharpapi-python-client
Version: 1.0.2
Summary: SharpAPI.com Python SDK Client - AI-Powered Workflow Automation API.
Home-page: https://sharpapi.com
License: MIT
Author: Dawid Makowski
Author-email: contact@sharpapi.com
Requires-Python: >=3.8,<4.0
Classifier: License :: OSI Approved :: MIT License
Classifier: Programming Language :: Python :: 3
Classifier: Programming Language :: Python :: 3.8
Classifier: Programming Language :: Python :: 3.9
Classifier: Programming Language :: Python :: 3.10
Classifier: Programming Language :: Python :: 3.11
Classifier: Programming Language :: Python :: 3.12
Requires-Dist: requests (>=2.25.1)
Project-URL: Documentation, https://sharpapi.com/documentation
Project-URL: Repository, https://github.com/sharpapi/sharpapi-python-client
